monitoring/__init__.py
monitoring/resource_monitoring.bat
monitoring/resource_monitoring.py
monitoring/resource_monitoring_runner.py
monitoring/resource_monitoring_runner.spec
monitoring/swagger_manager.py
monitoring/task_scheduler_script.py
resource_monitoring_bon-1.0.0.6.dist-info/METADATA
resource_monitoring_bon-1.0.0.6.dist-info/WHEEL
resource_monitoring_bon-1.0.0.6.dist-info/top_level.txt
resource_monitoring_bon-1.0.0.6.dist-info/RECORD
